fluepdot/__init__.py
fluepdot/fluepdot.py
fluepdot/mock_server.py
python_fluepdot-0.0.6.dist-info/licenses/LICENSE
python_fluepdot-0.0.6.dist-info/METADATA
python_fluepdot-0.0.6.dist-info/WHEEL
python_fluepdot-0.0.6.dist-info/top_level.txt
python_fluepdot-0.0.6.dist-info/RECORD
