Metadata-Version: 2.4
Name: python-fluepdot
Version: 0.0.6
Summary: A small collection of functions for interacting with a fluepdot module.
Author-email: KS-HTK <ks-htk@flipdot.org>
Project-URL: Homepage, https://github.com/KS-HTK/python-fluepdot
Project-URL: Bug-Tracker, https://github.com/KS-HTK/python-fluepdot/issues
Classifier: Programming Language :: Python :: 3
Classifier: License :: OSI Approved :: MIT License
Classifier: Operating System :: OS Independent
Requires-Python: >=3.7
License-File: LICENSE
Requires-Dist: requests
Dynamic: license-file
